odoo/addons/sale_order_line_remove/README.rst
odoo/addons/sale_order_line_remove/__init__.py
odoo/addons/sale_order_line_remove/__manifest__.py
odoo/addons/sale_order_line_remove/i18n/it.po
odoo/addons/sale_order_line_remove/i18n/sale_order_line_remove.pot
odoo/addons/sale_order_line_remove/models/__init__.py
odoo/addons/sale_order_line_remove/models/res_config_settings.py
odoo/addons/sale_order_line_remove/models/sale_order.py
odoo/addons/sale_order_line_remove/readme/CONTRIBUTORS.md
odoo/addons/sale_order_line_remove/readme/DESCRIPTION.md
odoo/addons/sale_order_line_remove/readme/USAGE.md
odoo/addons/sale_order_line_remove/static/description/icon.png
odoo/addons/sale_order_line_remove/static/description/index.html
odoo/addons/sale_order_line_remove/tests/__init__.py
odoo/addons/sale_order_line_remove/tests/test_sale_order_line.py
odoo/addons/sale_order_line_remove/views/res_config_settings_views.xml
odoo_addon_sale_order_line_remove-18.0.1.0.0.4.dist-info/METADATA
odoo_addon_sale_order_line_remove-18.0.1.0.0.4.dist-info/WHEEL
odoo_addon_sale_order_line_remove-18.0.1.0.0.4.dist-info/top_level.txt
odoo_addon_sale_order_line_remove-18.0.1.0.0.4.dist-info/RECORD
